Workbook

Sheet 1. Sources

Sheet 2. Raw Financials
A1: RAW FINANCIALS
A3: INCOME STATEMENT
A5: Metric | B5: 2023 | C5: 2024 | D5: 2025
A6: Revenue | B6: 13247 | C6: 15673 | D6: 17186
A7: Cost of Revenue | B7: 9850 | C7: 10949 | D7: 11690
A8: Gross Profit | B8: 3397 | C8: 4724 | D8: 5496
A9: Gross Margin | B9: =((B6-B7)/B6) -> 0.25643542 | C9: =((C6-C7)/C6) -> 0.30141007 | D9: =((D6-D7)/D6) -> 0.31979518
A10: R&D | B10: 1725 | C10: 1486 | D10: 1393
A11: Sales & Marketing | B11: 1533 | C11: 1392 | D11: 1426
A12: General Administrative Expenses | B12: 585 | C12: 481 | D12: 479
A13: Total Operating Expenses | B13: =SUM(B10:B12) -> 3843 | C13: =SUM(C10:C12) -> 3359 | D13: =SUM(D10:D12) -> 3298
A14: Operating Income | B14: -446 | C14: 1365 | D14: 2198
A15: Operating Margin | B15: =B14/B6 -> -0.033668 | C15: =C14/C6 -> 0.087092452 | D15: =D14/D6 -> 0.1278948
A16: Net Income | B16: -532 | C16: 1138 | D16: 2212
A19: CASH FLOW
A21: Metric | B21: 2023 | C21: 2024 | D21: 2025
A22: Operating Cash Flow | B22: 680 | C22: 2301 | D22: 2933
A23: Purchases of Property & Equipment (CE) | B23: 6 | C23: 17 | D23: 61
A24: Free Cash Flow | B24: =B22-B23 -> 674 | C24: =C22-C23 -> 2284 | D24: =D22-D23 -> 2872
A27: USERS
A29: Metric | B29: Q4 2024 | C29: Q4 2025 | D29: Q1 2026 | E29: NA
A30: MAUs | B30: 675 | C30: 751 | D30: 761
A31: Premium Subscribers | B31: 263 | C31: 290 | D31: 293
A32: Ad Supported Users | B32: 425 | C32: 476 | D32: 483
A35: REVENUE MIX
A37: Metric | B37: Q4 2024 | C37: Q4 2025 | D37: Q1 2026
A38: Premium Revenue | B38: 3705 | C38: 4013 | D38: 4148
A39: Ad Revenue | B39: 537 | C39: 446 | D39: 385
A42: SOURCE TRACKING
A44: Metric | B44: Report | C44: Page
A45: Revenue | B45: Annual Report 2025 | C45: 109 - f5
A46: MAUs | B46: Q4 2025 Deck | C46: 3

Sheet 3. Historical Financials
A1: HISTORICAL FINANCIALS
A3: GROWTH | F3: BUSINESS DRIVERS
A5: Metric | B5: 2023 | C5: 2024 | D5: 2025 | F5: Metric | G5: Q4 2024 | H5: Q4 2025 | I5: Q1 2026
A6: Revenue | B6: 13247 | C6: 15673 | D6: 17186 | F6: Monthly Active Users (MAUs) | G6: ='2. Raw Financials'!B30 -> 675 | H6: ='2. Raw Financials'!C30 -> 751 | I6: ='2. Raw Financials'!D30 -> 761
A7: Revenue Growth % | C7: =(C6-B6)/B6 -> 0.1831358 | D7: =(D6-C6)/C6 -> 0.096535443 | F7: Premium Subscribers | G7: ='2. Raw Financials'!B31 -> 263 | H7: ='2. Raw Financials'!C31 -> 290 | I7: ='2. Raw Financials'!D31 -> 293
F8: Ad-Supported Users | G8: ='2. Raw Financials'!B32 -> 425 | H8: ='2. Raw Financials'!C32 -> 476 | I8: ='2. Raw Financials'!D32 -> 483
F9: Total Revenue (€M) | G9: 4242 | H9: 4531 | I9: 4533
A10: PROFITABILITY | F10: Premium Revenue (€M) | G10: 3705 | H10: 4020 | I10: 4148
F11: Ad Revenue (€M) | G11: 537 | H11: 511 | I11: 386
A12: Metric | B12: 2023 | C12: 2024 | D12: 2025
A13: Gross Margin | B13: 0.2564 | C13: 0.3014 | D13: 0.3198 | F13: Premium Penetration | G13: =G7/G6 -> 0.38962963 | H13: =H7/H6 -> 0.3861518 | I13: =I7/I6 -> 0.38501971
A14: Operating Margin | B14: -0.0337 | C14: 0.0871 | D14: 0.1279 | F14: Ad Supported Mix | G14: =G8/G6 -> 0.62962963 | H14: =H8/H6 -> 0.63382157 | I14: =I8/I6 -> 0.6346912
A15: Net Margin | B15: ='2. Raw Financials'!B16/'2. Raw Financials'!B6 -> -0.040160036 | C15: ='2. Raw Financials'!C16/'2. Raw Financials'!C6 -> 0.072608945 | D15: ='2. Raw Financials'!D16/'2. Raw Financials'!D6 -> 0.12870941 | F15: Q.Revenue per Active User (€M) | G15: =G9/G6 -> 6.2844444 | H15: =H9/H6 -> 6.0332889 | I15: =I9/I6 -> 5.956636
A16: Free Cash Flow Margin | B16: ='2. Raw Financials'!B24/'2. Raw Financials'!B6 -> 0.050879444 | C16: ='2. Raw Financials'!C24/'2. Raw Financials'!C6 -> 0.14572832 | D16: ='2. Raw Financials'!D24/'2. Raw Financials'!D6 -> 0.16711277 | F16: Q. Revenue per Premium Subscriber (€M) | G16: =G10/G7 -> 14.087452 | H16: =H10/H7 -> 13.862069 | I16: =I10/I7 -> 14.156997
F17: Premium Revenue Mix | G17: =G10/G9 -> 0.87340877 | H17: =H10/H9 -> 0.88722136 | I17: =I10/I9 -> 0.91506728
F18: Ad Revenue Mix | G18: =G11/G10 -> 0.14493927 | H18: =H11/H10 -> 0.12711443 | I18: =I11/I10 -> 0.093056895
A19: COST STRUCTURE
F20: MAU Growth% | H20: =(H6-G6)/G6 -> 0.11259259 | I20: =(I6-H6)/H6 -> 0.013315579
A21: Metric | B21: 2023 | C21: 2024 | D21: 2025 | F21: Premium Subscriber Growth% | H21: =(H7-G7)/G7 -> 0.1026616 | I21: =(I7-H7)/H7 -> 0.010344828
A22: Cost of Revenue % | B22: ='2. Raw Financials'!B7/'2. Raw Financials'!B6 -> 0.74356458 | C22: ='2. Raw Financials'!C7/'2. Raw Financials'!C6 -> 0.69858993 | D22: ='2. Raw Financials'!D7/'2. Raw Financials'!D6 -> 0.68020482 | F22: Ad Supported Growth% | H22: =(H8-G8)/G8 -> 0.12 | I22: =(I8-H8)/H8 -> 0.014705882
A23: R&D % Revenue | B23: ='2. Raw Financials'!B10/'2. Raw Financials'!B6 -> 0.13021816 | C23: ='2. Raw Financials'!C10/'2. Raw Financials'!C6 -> 0.094812735 | D23: ='2. Raw Financials'!D10/'2. Raw Financials'!D6 -> 0.081054347
A24: Sales & Marketing % Revenue | B24: ='2. Raw Financials'!B11/'2. Raw Financials'!B6 -> 0.11572431 | C24: ='2. Raw Financials'!C11/'2. Raw Financials'!C6 -> 0.08881516 | D24: ='2. Raw Financials'!D11/'2. Raw Financials'!D6 -> 0.082974514
A25: G&A % Revenue | B25: ='2. Raw Financials'!B12/'2. Raw Financials'!B6 -> 0.044160942 | C25: ='2. Raw Financials'!C12/'2. Raw Financials'!C6 -> 0.030689721 | D25: ='2. Raw Financials'!D12/'2. Raw Financials'!D6 -> 0.027871523
A28: CASH GENERATION | F28: KPI | G28: Observation
F29: MAUs | G29: Positive growth, theres momentum but slower at the start of a new year
A30: Metric | B30: 2023 | C30: 2024 | D30: 2025 | F30: Premium Mix | G30: Increasing
A31: Operating Cash Flow | B31: ='2. Raw Financials'!B22 -> 680 | C31: ='2. Raw Financials'!C22 -> 2301 | D31: ='2. Raw Financials'!D22 -> 2933 | F31: Revenue per User | G31: Declining for overall user group, Increasing for Premium users
A32: Free Cash Flow | B32: ='2. Raw Financials'!B24 -> 674 | C32: ='2. Raw Financials'!C24 -> 2284 | D32: ='2. Raw Financials'!D24 -> 2872 | F32: Premium Penetration | G32: Stable around 38%, marginal decline
A33: Cash Conversion | B33: =B32/'2. Raw Financials'!B16 -> -1.2669173 | C33: =C32/'2. Raw Financials'!C16 -> 2.0070299 | D33: =D32/'2. Raw Financials'!D16 -> 1.2983725 | F33: Ad Revenue | G33: Declining

Sheet 4. Forecast Model
A1: FORECAST MODEL
A3: SCENARIO | B3: BEAR | F3: DELTA
F4: Rev Metrics | G4: =IF(B3="Bull",1.2,IF(B3="Bear",0.8,1)) -> 0.8
A5: Assumption | B5: 2026 | C5: 2027 | D5: 2028 | F5: Cost Metrics | G5: =IF(B3="Bull",0.8,IF(B3="Bear",1.2,1)) -> 1.2
A6: Revenue Growth | B6: =B41*$G$4 -> 0.072 | C6: =C41*$G$4 -> 0.064 | D6: =D41*$G$4 -> 0.056
A7: Gross Margin | B7: =B42*$G$4 -> 0.248 | C7: =C42*$G$4 -> 0.256 | D7: =D42*$G$4 -> 0.264
A8: R&D (% Revenue) | B8: =B43*$G$5 -> 0.096 | C8: =C43*$G$5 -> 0.084 | D8: =D43*$G$5 -> 0.072
A9: Sales & Marketing (% Revenue) | B9: =B44*$G$5 -> 0.0984 | C9: =C44*$G$5 -> 0.096 | D9: =D44*$G$5 -> 0.0936
A10: G&A (% Revenue) | B10: =B45*$G$5 -> 0.03 | C10: =C45*$G$5 -> 0.024 | D10: =D45*$G$5 -> 0.0204
A11: Free Cash Flow Margin | B11: =B46*$G$4 -> 0.096 | C11: =C46*$G$4 -> 0.104 | D11: =D46*$G$4 -> 0.112
A12: Net Margin % | B12: =B47*$G$4 -> 0.064 | C12: =C47*$G$4 -> 0.08 | D12: =D47*$G$4 -> 0.096
A14: FORECAST CALCULATIONS
A16: Metric | B16: Historical | E16: Forecasted
A17: Years | B17: 2023 | C17: 2024 | D17: 2025 | E17: 2026 | F17: 2027 | G17: 2028
A18: Revenue | B18: ='2. Raw Financials'!B6 -> 13247 | C18: ='2. Raw Financials'!C6 -> 15673 | D18: ='2. Raw Financials'!D6 -> 17186 | E18: =D18*(1+B6) -> 18423.392 | F18: =E18*(1+C6) -> 19602.489 | G18: =F18*(1+D6) -> 20700.228
A19: Gross Profit | B19: ='2. Raw Financials'!B8 -> 3397 | C19: ='2. Raw Financials'!C8 -> 4724 | D19: ='2. Raw Financials'!D8 -> 5496 | E19: =E18*B7 -> 4569.0012 | F19: =F18*C7 -> 5018.2372 | G19: =G18*D7 -> 5464.8603
A20: R&D | B20: ='2. Raw Financials'!B10 -> 1725 | C20: ='2. Raw Financials'!C10 -> 1486 | D20: ='2. Raw Financials'!D10 -> 1393 | E20: =E18*B8 -> 1768.6456 | F20: =F18*C8 -> 1646.6091 | G20: =G18*D8 -> 1490.4165
A21: Sales & Marketing | B21: ='2. Raw Financials'!B11 -> 1533 | C21: ='2. Raw Financials'!C11 -> 1392 | D21: ='2. Raw Financials'!D11 -> 1426 | E21: =E18*B9 -> 1812.8618 | F21: =F18*C9 -> 1881.839 | G21: =G18*D9 -> 1937.5414
A22: G&A | B22: ='2. Raw Financials'!B12 -> 585 | C22: ='2. Raw Financials'!C12 -> 481 | D22: ='2. Raw Financials'!D12 -> 479 | E22: =E18*B10 -> 552.70176 | F22: =F18*C10 -> 470.45974 | G22: =G18*D10 -> 422.28466
A23: Operating Expenses | B23: ='2. Raw Financials'!B13 -> 3843 | C23: ='2. Raw Financials'!C13 -> 3359 | D23: ='2. Raw Financials'!D13 -> 3298 | E23: =SUM(E20:E22) -> 4134.2092 | F23: =SUM(F20:F22) -> 3998.9078 | G23: =SUM(G20:G22) -> 3850.2425
A24: Operating Income | B24: ='2. Raw Financials'!B14 -> -446 | C24: ='2. Raw Financials'!C14 -> 1365 | D24: ='2. Raw Financials'!D14 -> 2198 | E24: =E19-E23 -> 434.79205 | F24: =F19-F23 -> 1019.3294 | G24: =G19-G23 -> 1614.6178
A25: Operating Margin | B25: ='2. Raw Financials'!B15 -> -0.033668 | C25: ='2. Raw Financials'!C15 -> 0.087092452 | D25: ='2. Raw Financials'!D15 -> 0.1278948 | E25: =E24/E18 -> 0.0236 | F25: =F24/F18 -> 0.052 | G25: =G24/G18 -> 0.078
A26: Net Income | B26: ='2. Raw Financials'!B16 -> -532 | C26: ='2. Raw Financials'!C16 -> 1138 | D26: ='2. Raw Financials'!D16 -> 2212 | E26: =E18*B12 -> 1179.0971 | F26: =F18*C12 -> 1568.1991 | G26: =G18*D12 -> 1987.2219
A27: Free Cash Flow | B27: ='2. Raw Financials'!B24 -> 674 | C27: ='2. Raw Financials'!C24 -> 2284 | D27: ='2. Raw Financials'!D24 -> 2872 | E27: =E18*B11 -> 1768.6456 | F27: =F18*C11 -> 2038.6589 | G27: =G18*D11 -> 2318.4256
A30: Key Assumptions
A31: 1. Revenue growth moderates as Spotify scales while margins continue expanding through operational efficiency and disciplined cost management. R&D and G&A are expected to decline as a percentage of revenue, reflecting operating leverage. Free cash flow is projected to improve alongside increasing profitability.
A35: 2. The 20% delta is calibrated to reflect realistic but meaningful market stress. Spotify's revenue growth has historically swung ~8-12pp across macro cycles, and a 20% relative shift on a 9% base (producing ~7-11% range) is consistent with that observed volatility. Cost assumptions follow a similar logic — G&A and S&M tend to grow stickier than revenue in downturns, making a 20% upward stress reasonable without being extreme.
A39: BASE CASE (LOCKED)
A40: Assumption | B40: 2026 | C40: 2027 | D40: 2028
A41: Revenue Growth | B41: 0.09 | C41: 0.08 | D41: 0.07
A42: Gross Margin | B42: 0.31 | C42: 0.32 | D42: 0.33
A43: R&D (% Revenue) | B43: 0.08 | C43: 0.07 | D43: 0.06
A44: Sales & Marketing (% Revenue) | B44: 0.082 | C44: 0.08 | D44: 0.078
A45: G&A (% Revenue) | B45: 0.025 | C45: 0.02 | D45: 0.017
A46: Free Cash Flow Margin | B46: 0.12 | C46: 0.13 | D46: 0.14
A47: Net Margin % | B47: 0.08 | C47: 0.1 | D47: 0.12
A50: Years | B50: 2023 | C50: 2024 | D50: 2025 | E50: 2026 | F50: 2027 | G50: 2028
A51: Operating Margin | B51: =B25 -> -0.033668 | C51: =C25 -> 0.087092452 | D51: =D25 -> 0.1278948 | E51: =E25 -> 0.0236 | F51: =F25 -> 0.052 | G51: =G25 -> 0.078
A52: Net Margin | B52: ='3. Historical Financials'!B15 -> -0.040160036 | C52: ='3. Historical Financials'!C15 -> 0.072608945 | D52: ='3. Historical Financials'!D15 -> 0.12870941 | E52: =B12 -> 0.064 | F52: =C12 -> 0.08 | G52: =D12 -> 0.096
A53: Free Cash Flow Margin | B53: ='3. Historical Financials'!B16 -> 0.050879444 | C53: ='3. Historical Financials'!C16 -> 0.14572832 | D53: ='3. Historical Financials'!D16 -> 0.16711277 | E53: =B11 -> 0.096 | F53: =C11 -> 0.104 | G53: =D11 -> 0.112

Sheet 5. Executive Dashboard
B1: SPOTIFY AT A GLANCE
B6: REVENUE | G6: GROSS MARGIN | L6: NET INCOME | Q6: FREE CASH FLOW
B8: €17.2B | G8: 0.32 | L8: €2.2B | Q8: €2.87B
B14: 0.097 | G14: 1.9pts | L14: 0.94 | Q14: 0.26
B38: Revenue continues to grow despite moderate growth rates | I38: Improving operating leverage drives stronger profitability and cash generation | O38: A declining cost base relative to revenue demonstrates improving operating efficiency.
B44: BUSINESS DRIVERS | I44: THESIS | K44: STRENGTH | N44: Margin expansion demonstrates improving operating leverage while maintaining user growth
B47: MAU | E47: 761 M | G47: 0.013
K48: RISK | N48: Revenue growth is slowing as Spotify matures and advertising remains more volatile than subscriptions
B49: PREMIUM SUBS | E49: 293 M | G49: 0.01
B51: PREMIUM MIX | E51: 0.385
K52: OUTLOOK | N52: Continued Premium subscriber growth and disciplined expense management position Spotify for sustained profitability and stronger free cash generation
B53: QUARTERLY PREMIUM APRU | E53: 0.1416
